[
  {
    "name":"Debit Object One",
    "value":120,
    "payed":false,
    "domId":"topayId_topay"
  },
  {
    "name":"Debit Object Two",
    "value":120,
    "payed":false,
    "domId":"topayId_topay"
  },
  {
   "name":"Debit Object Three",
    "value":120,
    "payed":false,
    "domId":"topayId_topay"
  },
  {
    "name":"Debit Object Four",
    "value":120,
    "payed":true,
    "domId":"topayId_topay"
  },
  {
    "name":"Debit Object Five",
    "value":120,
    "payed":true,
    "domId":"topayId_topay"
  },
  {
    "name":"Debit Object Six",
    "value":120,
    "payed":true,
    "domId":"topayId_topay"
  },
  {
    "name":"Debit Object Seven",
    "value":120,
    "payed":false,
    "domId":"topayId_topay"
  },
  {
    "name":"Debit Object Eight",
    "value":120,
    "payed":false,
    "domId":"topayId_topay"
  },
  {
    "name":"Debit Object Nine",
    "value":120,
    "payed":false,
    "domId":"topayId_topay"
  },
  {
    "name":"Debit Object Ten",
    "value":180,
    "payed":false,
    "domId":"topayId_topay"
  },
  {
    "name":"Debit Object Eleven",
    "value":190,
    "payed":false,
    "domId":"topayId_topay"
  },
  {
    "name":"Debit Object Twelve",
    "value":200,
    "payed":false,
    "domId":"topayId_topay"
  },
  {
    "name":"Debit Object Thirteen",
    "value":320,
    "payed":true,
    "domId":"topayId_topay"
  },
  {
    "name":"Debit Object Fourteen",
    "value":320,
    "payed":false,
    "domId":"topayId_topay"
  },
  {
    "name":"Debit Object Fifteen",
    "value":320,
    "payed":true,
    "domId":"topayId_topay"
  }
]